fakeoai/__init__.py
fakeoai/server.py
fakeoai/flask/static/_next/static/3Ogfe3rbepk5p-l8Fm-xW/_buildManifest.js
fakeoai/flask/static/_next/static/3Ogfe3rbepk5p-l8Fm-xW/_ssgManifest.js
fakeoai/flask/static/_next/static/chunks/2178.18cbce9703f1716c.js
fakeoai/flask/static/_next/static/chunks/2186.cabe8d2968afacb8.js
fakeoai/flask/static/_next/static/chunks/3754-163b39ce431131bc.js
fakeoai/flask/static/_next/static/chunks/3975-7f17a9769fd1a61d.js
fakeoai/flask/static/_next/static/chunks/3a34cc27-e83cff9ee2ba2afc.js
fakeoai/flask/static/_next/static/chunks/5017-bdd3eb6219fbc9e9.js
fakeoai/flask/static/_next/static/chunks/5054-0657d7351436bb5c.js
fakeoai/flask/static/_next/static/chunks/5187.d6f3e7be8bddb1d0.js
fakeoai/flask/static/_next/static/chunks/5288.655e15d0328160bd.js
fakeoai/flask/static/_next/static/chunks/6875.234da06b9a80ed0b.js
fakeoai/flask/static/_next/static/chunks/6951.e7d1dd0f30b42e30.js
fakeoai/flask/static/_next/static/chunks/6952.8ad3cdd527fc5245.js
fakeoai/flask/static/_next/static/chunks/718.9483197b3c23f16f.js
fakeoai/flask/static/_next/static/chunks/7549-122f729dc49e6850.js
fakeoai/flask/static/_next/static/chunks/8400.229d5c975f2f96fb.js
fakeoai/flask/static/_next/static/chunks/9826.be1c530080db6526.js
fakeoai/flask/static/_next/static/chunks/framework-31ffa51d236da229.js
fakeoai/flask/static/_next/static/chunks/main-6da2aad3a6c32aae.js
fakeoai/flask/static/_next/static/chunks/webpack-ebfc6af85ce22ba2.js
fakeoai/flask/static/_next/static/chunks/pages/[[...default]]-bc9a420e8e08747c.js
fakeoai/flask/static/_next/static/chunks/pages/_app-02ec810d9d83e499.js
fakeoai/flask/static/_next/static/chunks/pages/_error-dfd7db9208d5bc06.js
fakeoai/flask/static/_next/static/chunks/pages/admin-2cb1ade3e79e149d.js
fakeoai/flask/static/_next/static/chunks/pages/bypass-4782eea63108c9bc.js
fakeoai/flask/static/_next/static/chunks/pages/gpts-f218063f1aa72d2c.js
fakeoai/flask/static/_next/static/chunks/pages/search-f969bf847681b2ce.js
fakeoai-0.1.6.dist-info/LICENSE
fakeoai-0.1.6.dist-info/METADATA
fakeoai-0.1.6.dist-info/WHEEL
fakeoai-0.1.6.dist-info/top_level.txt
fakeoai-0.1.6.dist-info/RECORD
